sntd/__init__.py
sntd/coetools.py
sntd/curve_io.py
sntd/fitting.py
sntd/ml.py
sntd/mldata.py
sntd/models.py
sntd/old_fitting.py
sntd/simulation.py
sntd/survey_cosmo.py
sntd/test_sntd.py
sntd/util.py
sntd/batch/__init__.py
sntd/batch/run_sntd.py
sntd/batch/run_sntd_init.py
sntd/batch/run_sntd_init_par.py
sntd/batch/run_sntd_par.py
sntd-2.5.7.dist-info/METADATA
sntd-2.5.7.dist-info/WHEEL
sntd-2.5.7.dist-info/top_level.txt
sntd-2.5.7.dist-info/RECORD
