Metadata-Version: 2.4
Name: sntd
Version: 2.5.7
Author: Justin Pierel
Author-email: Justin Pierel & Steve Rodney <jpierel@stsci.edu>
License: BSD
Project-URL: Homepage, https://sntd.readthedocs.org
Requires-Python: >=3.0
Requires-Dist: numpy
Requires-Dist: scipy
Requires-Dist: cython
Requires-Dist: sncosmo
Requires-Dist: astropy
Requires-Dist: matplotlib
Requires-Dist: dynesty
Requires-Dist: pyParz
Requires-Dist: scikit-learn
Requires-Dist: iminuit>=2.31.1
Requires-Dist: corner
Requires-Dist: pandas
Dynamic: author
